{
    "Description" : {
        "Id" : "PortraitPreset_133",
        "Name" : "PortraitPreset_133",
        "Details" : "",
        "Icon" : ""
    },
    "DataManager" : null,
    "backgroundColor" : {
        "r" : 0,
        "g" : 0,
        "b" : 0,
        "a" : 0
    },
    "headMesh" : 0.6689801,
    "hairMesh" : 4,
    "beardMesh" : 0,
    "suitMesh" : 9,
    "scar" : 0,
    "lightRig" : 5,
    "cameraPosition" : 3,
    "complexionTex" : 4,
    "eyebrowTex" : 1,
    "tattooTex" : 5,
    "actualTattooTex" : 0,
    "weights" : [
        25,
        102,
        7.312735,
        1.127741,
        13,
        5
    ],
    "browOffsetY" : -0.00343,
    "browOffsetZ" : 0.00122,
    "noseBridgeScale" : -0.1757811,
    "noseTipScale" : 0.032,
    "chinScale" : -0.032,
    "cheekOffsetY" : 0.002910431,
    "eyeWidth" : 0.03640965,
    "jawWidth" : 0.07310843,
    "animation" : 2,
    "isCommander" : false,
    "skinToneId" : "Skin_07",
    "eyeColorId" : "Eye_03",
    "hairRootId" : "Hair_12",
    "hairTipId" : "Hair_06",
    "tattooColorId" : "Tattoo_08",
    "lipColorId" : "Lip_13"
}